Anrok/__init__.py
Anrok/main.py
anrok-0.1.1.dist-info/METADATA
anrok-0.1.1.dist-info/WHEEL
anrok-0.1.1.dist-info/entry_points.txt
anrok-0.1.1.dist-info/top_level.txt
anrok-0.1.1.dist-info/RECORD
